mdtoreveal.py
mdtoreveal-0.4.dist-info/METADATA
mdtoreveal-0.4.dist-info/WHEEL
mdtoreveal-0.4.dist-info/entry_points.txt
mdtoreveal-0.4.dist-info/top_level.txt
mdtoreveal-0.4.dist-info/RECORD
