Metadata-Version: 2.4
Name: mdtoreveal
Version: 0.4
Summary: Transform a flat markdown to a reveal.js presentation.
Author-email: Julien Palard <julien@palard.fr>
License-Expression: MIT
Project-URL: Homepage, https://git.afpy.org/mdk/mdtoreveal
Classifier: Development Status :: 5 - Production/Stable
Classifier: Intended Audience :: Developers
Classifier: Natural Language :: English
Classifier: Programming Language :: Python :: 3
Requires-Python: >=3.6
Requires-Dist: jinja2
Requires-Dist: requests
Requires-Dist: markdown
Provides-Extra: dev
Requires-Dist: black; extra == "dev"
Requires-Dist: build; extra == "dev"
Requires-Dist: isort; extra == "dev"
Requires-Dist: mypy; extra == "dev"
Requires-Dist: pylint; extra == "dev"
Requires-Dist: pytest; extra == "dev"
Requires-Dist: tox; extra == "dev"
Requires-Dist: twine; extra == "dev"
Requires-Dist: types-requests; extra == "dev"
